AUTHORS.rst
LICENSE
MANIFEST.in
pyproject.toml
setup.cfg
setup.py
csrc/_wsq.c
csrc/commonnbis/src/lib/fet/allocfet.c
csrc/commonnbis/src/lib/fet/delfet.c
csrc/commonnbis/src/lib/fet/extrfet.c
csrc/commonnbis/src/lib/fet/freefet.c
csrc/commonnbis/src/lib/fet/lkupfet.c
csrc/commonnbis/src/lib/fet/nistcom.c
csrc/commonnbis/src/lib/fet/printfet.c
csrc/commonnbis/src/lib/fet/readfet.c
csrc/commonnbis/src/lib/fet/strfet.c
csrc/commonnbis/src/lib/fet/updatfet.c
csrc/commonnbis/src/lib/fet/writefet.c
csrc/commonnbis/src/lib/ioutil/dataio.c
csrc/commonnbis/src/lib/ioutil/filesize.c
csrc/commonnbis/src/lib/util/bres.c
csrc/commonnbis/src/lib/util/bubble.c
csrc/commonnbis/src/lib/util/computil.c
csrc/commonnbis/src/lib/util/fatalerr.c
csrc/commonnbis/src/lib/util/invbyte.c
csrc/commonnbis/src/lib/util/invbytes.c
csrc/commonnbis/src/lib/util/memalloc.c
csrc/commonnbis/src/lib/util/ssxstats.c
csrc/commonnbis/src/lib/util/syserr.c
csrc/commonnbis/src/lib/util/ticks.c
csrc/commonnbis/src/lib/util/time.c
csrc/imgtools/src/lib/jpegl/decoder.c
csrc/imgtools/src/lib/jpegl/encoder.c
csrc/imgtools/src/lib/jpegl/huff.c
csrc/imgtools/src/lib/jpegl/huftable.c
csrc/imgtools/src/lib/jpegl/imgdat.c
csrc/imgtools/src/lib/jpegl/ppi.c
csrc/imgtools/src/lib/jpegl/sd4util.c
csrc/imgtools/src/lib/jpegl/tableio.c
csrc/imgtools/src/lib/jpegl/util.c
csrc/imgtools/src/lib/wsq/cropcoeff.c
csrc/imgtools/src/lib/wsq/decoder.c
csrc/imgtools/src/lib/wsq/encoder.c
csrc/imgtools/src/lib/wsq/globals.c
csrc/imgtools/src/lib/wsq/huff.c
csrc/imgtools/src/lib/wsq/ppi.c
csrc/imgtools/src/lib/wsq/sd14util.c
csrc/imgtools/src/lib/wsq/tableio.c
csrc/imgtools/src/lib/wsq/tree.c
csrc/imgtools/src/lib/wsq/util.c
csrc/commonnbis/include/defs.h
csrc/commonnbis/include/fet.h
csrc/commonnbis/include/invbyte.h
csrc/commonnbis/include/memalloc.h
csrc/commonnbis/include/usebsd.h
csrc/commonnbis/include/util.h
csrc/imgtools/include/computil.h
csrc/imgtools/include/dataio.h
csrc/imgtools/include/ihead.h
wsq2.egg-info/PKG-INFO
wsq2.egg-info/SOURCES.txt
wsq2.egg-info/dependency_links.txt
wsq2.egg-info/requires.txt
wsq2.egg-info/top_level.txt
